lapis/cli/__init__.py
lapis/cli/simulate.py
lapis/controller.py
lapis/cost.py
lapis/drone.py
lapis/job.py
lapis/job_io/__init__.py
lapis/job_io/htcondor.py
lapis/job_io/swf.py
lapis/monitor/__init__.py
lapis/monitor/cobald.py
lapis/monitor/general.py
lapis/pool.py
lapis/pool_io/__init__.py
lapis/pool_io/htcondor.py
lapis/pool_io/machines.py
lapis/scheduler.py
lapis/simulator.py
lapis_sim-0.4.2.dist-info/LICENSE
lapis_sim-0.4.2.dist-info/WHEEL
lapis_sim-0.4.2.dist-info/METADATA
lapis_sim-0.4.2.dist-info/RECORD
